{
    "perf": [
        {
            "loss": -65.34453582763672,
            "val_loss": -22.269012451171875
        },
        {
            "loss": -95.7930679321289,
            "val_loss": -7.815523624420166
        },
        {
            "loss": -104.46650695800781,
            "val_loss": -7.121454238891602
        },
        {
            "loss": -111.40692138671875,
            "val_loss": -48.40890884399414
        },
        {
            "loss": -116.28716278076172,
            "val_loss": 10.3554105758667
        },
        {
            "loss": -121.32452392578125,
            "val_loss": -35.491600036621094
        },
        {
            "loss": -123.95073699951172,
            "val_loss": -24.482595443725586
        },
        {
            "loss": -128.43287658691406,
            "val_loss": -18.985340118408203
        },
        {
            "loss": -131.36062622070312,
            "val_loss": -15.58437728881836
        },
        {
            "loss": -133.45724487304688,
            "val_loss": -45.13619613647461
        }
    ]
}